simbi/__init__.py
simbi/bimodal.py
simbi/coordinate_handler.py
simbi/number_converserions.py
simbi/utils.py
simbi/bec/__init__.py
simbi/bec/tf_ode_solver.py
simbi/bec/thomas_fermi.py
simbi/thermal/__init__.py
simbi/thermal/custom_polylog.py
simbi/thermal/enhanced_bose.py
simbi-0.0.1.dist-info/LICENSE.txt
simbi-0.0.1.dist-info/METADATA
simbi-0.0.1.dist-info/WHEEL
simbi-0.0.1.dist-info/top_level.txt
simbi-0.0.1.dist-info/RECORD
