Metadata-Version: 2.1
Name: simbi
Version: 0.0.1
Summary: Simulates a bimodal ultracold atom clouds.
Home-page: https://lucas-hofer.com/
Author: Lucas Hofer
Keywords: BEC
Requires-Python: <4,>=3.9
License-File: LICENSE.txt
Requires-Dist: numpy
Requires-Dist: scipy
